agent_ix/VERSION
agent_ix/__init__.py
agent_ix/__main__.py
agent_ix/base.py
agent_ix/cli.py
agent_ix/ix_env.py
agent_ix-0.6.dist-info/LICENSE
agent_ix-0.6.dist-info/METADATA
agent_ix-0.6.dist-info/WHEEL
agent_ix-0.6.dist-info/entry_points.txt
agent_ix-0.6.dist-info/top_level.txt
agent_ix-0.6.dist-info/RECORD
